django_gum-1.1.1.dist-info/DESCRIPTION.rst
django_gum-1.1.1.dist-info/METADATA
django_gum-1.1.1.dist-info/RECORD
django_gum-1.1.1.dist-info/WHEEL
django_gum-1.1.1.dist-info/metadata.json
django_gum-1.1.1.dist-info/pbr.json
django_gum-1.1.1.dist-info/top_level.txt
gum/__init__.py
gum/apps.py
gum/indexer.py
gum/managers.py
gum/models.py
gum/settings.py
gum/signals.py
gum/tasks.py
gum/utils.py
gum/management/__init__.py
gum/management/commands/__init__.py
gum/management/commands/gum.py
