Metadata-Version: 2.0
Name: django-gum
Version: 1.1.1
Summary: Elasticsearch client with Django support.
Home-page: https://github.com/marcosgabarda/django-gum
Author: Marcos Gabarda
Author-email: hey@marcosgabarda.com
License: UNKNOWN
Platform: UNKNOWN
Classifier: Environment :: Web Environment
Classifier: Framework :: Django
Classifier: Intended Audience :: Developers
Classifier: License :: OSI Approved :: MIT License
Classifier: Operating System :: OS Independent
Classifier: Programming Language :: Python
Requires-Dist: celery
Requires-Dist: django (>=1.5)
Requires-Dist: elasticsearch (>=1.0.0,<2.0.0)
Requires-Dist: six
